cppython_vcpkg/__init__.py
cppython_vcpkg/plugin.py
cppython_vcpkg-0.4.0.dist-info/entry_points.txt
cppython_vcpkg-0.4.0.dist-info/WHEEL
cppython_vcpkg-0.4.0.dist-info/METADATA
cppython_vcpkg-0.4.0.dist-info/license_files/LICENSE.md
cppython_vcpkg-0.4.0.dist-info/RECORD
