Metadata-Version: 2.1
Name: cppython-vcpkg
Version: 0.4.0
Summary: A plugin for CPPython that enables vcpkg support for CMake projects
License: MIT
Author-email: Synodic Software <contact@synodic.software>
Requires-Python: >=3.10
Requires-Dist: cppython-core>=0.3.3.dev0
Project-URL: homepage, https://github.com/Synodic-Software/CPPython-Vcpkg
Project-URL: repository, https://github.com/Synodic-Software/CPPython-Vcpkg
